knotty/__init__.py
knotty/core.py
knotty/exporters.py
knotty/meters.py
knotty/registry.py
knotty-0.4.0.dist-info/LICENSE
knotty-0.4.0.dist-info/METADATA
knotty-0.4.0.dist-info/WHEEL
knotty-0.4.0.dist-info/top_level.txt
knotty-0.4.0.dist-info/RECORD
