Metadata-Version: 2.1
Name: knotty
Version: 0.4.0
Summary: Application Performance Monitoring Made Easy
Home-page: https://github.com/kahinton/knotty
Author: Kyle Hinton
License: MIT
Platform: UNKNOWN
Requires-Python: >=3.7
Requires-Dist: psutil
Requires-Dist: flask
Requires-Dist: requests
Requires-Dist: numpy
